PolUVR/README.md
PolUVR/__init__.py
PolUVR/models-scores.json
PolUVR/separator/__init__.py
PolUVR/separator/architectures/__init__.py
PolUVR/separator/architectures/demucs_separator.py
PolUVR/separator/architectures/mdx_separator.py
PolUVR/separator/architectures/mdxc_separator.py
PolUVR/separator/architectures/vr_separator.py
PolUVR/separator/common_separator.py
PolUVR/separator/roformer/README.md
PolUVR/separator/roformer/__init__.py
PolUVR/separator/roformer/bs_roformer_config.py
PolUVR/separator/roformer/bs_roformer_validator.py
PolUVR/separator/roformer/configuration_normalizer.py
PolUVR/separator/roformer/mel_band_roformer_config.py
PolUVR/separator/roformer/mel_band_roformer_validator.py
PolUVR/separator/roformer/model_configuration.py
PolUVR/separator/roformer/model_loading_result.py
PolUVR/separator/roformer/parameter_validation_error.py
PolUVR/separator/roformer/parameter_validator.py
PolUVR/separator/roformer/roformer_loader.py
PolUVR/separator/separator.py
PolUVR/separator/uvr_lib_v5/__init__.py
PolUVR/separator/uvr_lib_v5/demucs/__init__.py
PolUVR/separator/uvr_lib_v5/demucs/__main__.py
PolUVR/separator/uvr_lib_v5/demucs/apply.py
PolUVR/separator/uvr_lib_v5/demucs/demucs.py
PolUVR/separator/uvr_lib_v5/demucs/filtering.py
PolUVR/separator/uvr_lib_v5/demucs/hdemucs.py
PolUVR/separator/uvr_lib_v5/demucs/htdemucs.py
PolUVR/separator/uvr_lib_v5/demucs/model.py
PolUVR/separator/uvr_lib_v5/demucs/model_v2.py
PolUVR/separator/uvr_lib_v5/demucs/pretrained.py
PolUVR/separator/uvr_lib_v5/demucs/repo.py
PolUVR/separator/uvr_lib_v5/demucs/spec.py
PolUVR/separator/uvr_lib_v5/demucs/states.py
PolUVR/separator/uvr_lib_v5/demucs/tasnet.py
PolUVR/separator/uvr_lib_v5/demucs/tasnet_v2.py
PolUVR/separator/uvr_lib_v5/demucs/transformer.py
PolUVR/separator/uvr_lib_v5/demucs/utils.py
PolUVR/separator/uvr_lib_v5/mdxnet.py
PolUVR/separator/uvr_lib_v5/mixer.ckpt
PolUVR/separator/uvr_lib_v5/modules.py
PolUVR/separator/uvr_lib_v5/playsound.py
PolUVR/separator/uvr_lib_v5/pyrb.py
poluvr-1.11.0.dist-info/METADATA
poluvr-1.11.0.dist-info/WHEEL
poluvr-1.11.0.dist-info/entry_points.txt
poluvr-1.11.0.dist-info/licenses/LICENSE
poluvr-1.11.0.dist-info/RECORD
